LICENSE
README.md
pyproject.toml
optiland/__init__.py
optiland/aberrations.py
optiland/aperture.py
optiland/apodization.py
optiland/coatings.py
optiland/coordinate_system.py
optiland/distribution.py
optiland/fields.py
optiland/jones.py
optiland/mtf.py
optiland/optic.py
optiland/paraxial.py
optiland/physical_apertures.py
optiland/pickup.py
optiland/psf.py
optiland/scatter.py
optiland/solves.py
optiland/wavefront.py
optiland/wavelength.py
optiland/zernike.py
optiland.egg-info/PKG-INFO
optiland.egg-info/SOURCES.txt
optiland.egg-info/dependency_links.txt
optiland.egg-info/requires.txt
optiland.egg-info/top_level.txt
optiland/analysis/__init__.py
optiland/analysis/distortion.py
optiland/analysis/encircled_energy.py
optiland/analysis/field_curvature.py
optiland/analysis/grid_distortion.py
optiland/analysis/pupil_aberration.py
optiland/analysis/ray_fan.py
optiland/analysis/rms_vs_field.py
optiland/analysis/spot_diagram.py
optiland/analysis/y_ybar.py
optiland/database/__init__.py
optiland/database/catalog-n2.yml
optiland/database/catalog-nk.yml
optiland/database/catalog_nk.csv
optiland/database/generate_csv_database.py
optiland/database/glass_model_coefficients.npy
optiland/database/data-n2/glass/AMTIR-1/Ensley.yml
optiland/database/data-n2/glass/AMTIR-2/Ensley.yml
optiland/database/data-n2/glass/AMTIR-6/Ensley.yml
optiland/database/data-n2/glass/BGG/Flom.yml
optiland/database/data-n2/glass/BK10/White.yml
optiland/database/data-n2/glass/BK7/Adair.yml
optiland/database/data-n2/glass/BK7/Ensley.yml
optiland/database/data-n2/glass/BK7/Flom.yml
optiland/database/data-n2/main/AgCl/Adair.yml
optiland/database/data-n2/main/AgGaS2/Jansonas-e.yml
optiland/database/data-n2/main/AgGaS2/Jansonas-o.yml
optiland/database/data-n2/main/AgGaSe2/Pigeon.yml
optiland/database/data-n2/main/Al2O3/Adair-e.yml
optiland/database/data-n2/main/Al2O3/Adair-o.yml
optiland/database/data-n2/main/Al2O3/DeSalvo.yml
optiland/database/data-n2/main/Al2O3/Patwardhan.yml
optiland/database/data-n2/main/BaB2O4/DeSalvo.yml
optiland/database/data-n2/main/BaF2/Adair.yml
optiland/database/data-n2/main/BaF2/DeSalvo.yml
optiland/database/data-n2/main/BaF2/Ensley.yml
