Metadata-Version: 2.2
Name: optiland
Version: 0.2.6
Author-email: Kramer Harrison <kdanielharrison@gmail.com>
License: MIT License
Project-URL: Homepage, https://github.com/HarrisonKramer/optiland
Classifier: Programming Language :: Python :: 3
Classifier: Operating System :: OS Independent
Requires-Python: >=3.9
License-File: LICENSE
Requires-Dist: setuptools
Requires-Dist: numpy
Requires-Dist: scipy
Requires-Dist: pandas
Requires-Dist: pyyaml
Requires-Dist: matplotlib
Requires-Dist: vtk
Requires-Dist: tabulate
Requires-Dist: numba
Requires-Dist: requests
Requires-Dist: seaborn
